Metadata-Version: 1.1
Name: wfepy
Version: 0.1
Summary: Workflow Engine for Python
Home-page: https://github.com/redhat-aqe/wfepy
Author: Filip Poboril
Author-email: fpoboril@redhat.com
License: MIT
Download-URL: https://github.com/redhat-aqe/wfepy/archive/v0.1.tar.gz
Keywords: Workflow,Workflow Engine
Platform: UNKNOWN
Classifier: Development Status :: 5 - Production/Stable
Classifier: Intended Audience :: Developers
Classifier: License :: OSI Approved :: MIT License
Classifier: Natural Language :: English
Classifier: Programming Language :: Python :: 3 :: Only
Classifier: Programming Language :: Python :: 3.5
Classifier: Programming Language :: Python :: 3.6
Classifier: Programming Language :: Python :: 3.7
Classifier: Topic :: Software Development :: Libraries
